MANIFEST.in
README.txt
setup.cfg
setup.py
docs/HISTORY.txt
docs/INSTALL.txt
docs/LICENSE.GPL
docs/LICENSE.txt
ploomcake/__init__.py
ploomcake/__init__.pyc
ploomcake.theme.egg-info/PKG-INFO
ploomcake.theme.egg-info/SOURCES.txt
ploomcake.theme.egg-info/dependency_links.txt
ploomcake.theme.egg-info/entry_points.txt
ploomcake.theme.egg-info/namespace_packages.txt
ploomcake.theme.egg-info/not-zip-safe
ploomcake.theme.egg-info/requires.txt
ploomcake.theme.egg-info/top_level.txt
ploomcake/theme/__init__.py
ploomcake/theme/configure.zcml
ploomcake/theme/profiles.zcml
ploomcake/theme/setuphandlers.py
ploomcake/theme/skins.zcml
ploomcake/theme/tests.py
ploomcake/theme/version.txt
ploomcake/theme/browser/__init__.py
ploomcake/theme/browser/colophon.pt
ploomcake/theme/browser/common.py
ploomcake/theme/browser/configure.zcml
ploomcake/theme/browser/footer.pt
ploomcake/theme/browser/interfaces.py
ploomcake/theme/browser/sections.pt
ploomcake/theme/browser/selector.pt
ploomcake/theme/browser/images/README.txt
ploomcake/theme/browser/js/collapsedheading.js
ploomcake/theme/browser/js/search.js
ploomcake/theme/profiles/default/cssregistry.xml
ploomcake/theme/profiles/default/jsregistry.xml
ploomcake/theme/profiles/default/metadata.xml
ploomcake/theme/profiles/default/ploomcake.theme_various.txt
ploomcake/theme/profiles/default/propertiestool.xml
ploomcake/theme/profiles/default/skins.xml
ploomcake/theme/profiles/default/tinymce.xml
ploomcake/theme/profiles/default/viewlets.xml
ploomcake/theme/skins/ploomcake_theme/apple-touch-icon-high.png
ploomcake/theme/skins/ploomcake_theme/apple-touch-icon-low.png
ploomcake/theme/skins/ploomcake_theme/apple-touch-icon-medium.png
ploomcake/theme/skins/ploomcake_theme/apple-touch-icon-precomposed-low.png
ploomcake/theme/skins/ploomcake_theme/dot-current.png
ploomcake/theme/skins/ploomcake_theme/dot.png
ploomcake/theme/skins/ploomcake_theme/favicon.ico
ploomcake/theme/skins/ploomcake_theme/language.png
ploomcake/theme/skins/ploomcake_theme/logo-mobile.png
ploomcake/theme/skins/ploomcake_theme/logo.png
ploomcake/theme/skins/ploomcake_theme/logoIcon.png
ploomcake/theme/skins/ploomcake_theme/main_template.pt
ploomcake/theme/skins/ploomcake_theme/menu-selected.png
ploomcake/theme/skins/ploomcake_theme/navigator.png
