Metadata-Version: 1.0
Name: ploomcake.theme
Version: 1.8
Summary: An installable theme for Plone 4 based on redomino.css3theme
Home-page: https://github.com/ploomcake/ploomcake.theme
Author: Andrea D'Este
Author-email: andrea.deste@redomino.com
License: GPL
Platform: UNKNOWN
Classifier: Framework :: Plone
Classifier: Programming Language :: Python
